<?xml version="1.0" encoding="utf-8" ?>
<dwsync>
<file name="spacer.gif" server="ftp.chado.1gb.ru/http/" local="130013632200000000" remote="130013632200000000" />
<file name="menuseparator.png" server="ftp.chado.1gb.ru/http/" local="130013632200000000" remote="130013632200000000" />
<file name="subitem.png" server="ftp.chado.1gb.ru/http/" local="130013632200000000" remote="130013632200000000" />
<file name="footer.png" server="ftp.chado.1gb.ru/http/" local="130013632200000000" remote="130013632200000000" />
<file name="blockcontentbullets1.png" server="ftp.chado.1gb.ru/http/" local="130013632200000000" remote="130013632200000000" />
<file name="vsubitem.png" server="ftp.chado.1gb.ru/http/" local="130013632200000000" remote="130013632200000000" />
<file name="postbullets.png" server="ftp.chado.1gb.ru/http/" local="130013632200000000" remote="130013632200000000" />
<file name="block.png" server="ftp.chado.1gb.ru/http/" local="130013632200000000" remote="130013632200000000" />
<file name="blockcontent.png" server="ftp.chado.1gb.ru/http/" local="130013632200000000" remote="130013632200000000" />
<file name="vmenublock.png" server="ftp.chado.1gb.ru/http/" local="130013632200000000" remote="130013632200000000" />
<file name="blockcontentbullets.png" server="ftp.chado.1gb.ru/http/" local="130013632200000000" remote="130013632200000000" />
<file name="blockcontent_b.png" server="ftp.chado.1gb.ru/http/" local="130013632200000000" remote="130013632200000000" />
<file name="blockcontent_t.png" server="ftp.chado.1gb.ru/http/" local="130013632200000000" remote="130013632200000000" />
<file name="sheet.png" server="ftp.chado.1gb.ru/http/" local="130013632200000000" remote="130013632200000000" />
<file name="footerbullets.png" server="ftp.chado.1gb.ru/http/" local="130013632200000000" remote="130013632200000000" />
<file name="printButton.png" server="ftp.chado.1gb.ru/http/" local="130013632200000000" remote="130013632200000000" />
<file name="footer_b.png" server="ftp.chado.1gb.ru/http/" local="130013632200000000" remote="130013632200000000" />
<file name="block_b.png" server="ftp.chado.1gb.ru/http/" local="130013632200000000" remote="130013632200000000" />
<file name="block_t.png" server="ftp.chado.1gb.ru/http/" local="130013632200000000" remote="130013632200000000" />
<file name="edit.png" server="ftp.chado.1gb.ru/http/" local="130013632200000000" remote="130013632200000000" />
<file name="edit_unpublished.png" server="ftp.chado.1gb.ru/http/" local="130013632200000000" remote="130013632200000000" />
<file name="vmenublock_b.png" server="ftp.chado.1gb.ru/http/" local="130013632200000000" remote="130013632200000000" />
<file name="vmenublock_t.png" server="ftp.chado.1gb.ru/http/" local="130013632200000000" remote="130013632200000000" />
<file name="emailButton.png" server="ftp.chado.1gb.ru/http/" local="130013632200000000" remote="130013632200000000" />
<file name="pdf_button.png" server="ftp.chado.1gb.ru/http/" local="130013632200000000" remote="130013632200000000" />
<file name="sheet_t.png" server="ftp.chado.1gb.ru/http/" local="130013632200000000" remote="130013632200000000" />
<file name="postquote.png" server="ftp.chado.1gb.ru/http/" local="130013632200000000" remote="130013632200000000" />
<file name="blockheader.png" server="ftp.chado.1gb.ru/http/" local="130013632200000000" remote="130013632200000000" />
<file name="sheet_b.png" server="ftp.chado.1gb.ru/http/" local="130013632200000000" remote="130013632200000000" />
<file name="vmenublockheader.png" server="ftp.chado.1gb.ru/http/" local="130013632200000000" remote="130013632200000000" />
<file name="nav1.png" server="ftp.chado.1gb.ru/http/" local="130013632200000000" remote="130013632200000000" />
<file name="livemarks.png" server="ftp.chado.1gb.ru/http/" local="130013632200000000" remote="130013632200000000" />
<file name="menuitem.png" server="ftp.chado.1gb.ru/http/" local="130013632200000000" remote="130013632200000000" />
<file name="button.png" server="ftp.chado.1gb.ru/http/" local="130013632200000000" remote="130013632200000000" />
<file name="vmenuitem.png" server="ftp.chado.1gb.ru/http/" local="130013632200000000" remote="130013632200000000" />
<file name="nav.png" server="ftp.chado.1gb.ru/http/" local="130013632200000000" remote="130013632200000000" />
<file name="fon1.png" server="ftp.chado.1gb.ru/http/" local="130014390600000000" remote="130014390600000000" />
<file name="preview.jpg" server="ftp.chado.1gb.ru/http/" local="130013632200000000" remote="130013632200000000" />
<file name="page_gl.png" server="ftp.chado.1gb.ru/http/" local="130013632200000000" remote="130013632200000000" />
<file name="header-1.png" server="ftp.chado.1gb.ru/http/" local="130013632200000000" remote="130013632200000000" />
<file name="header.png" server="ftp.chado.1gb.ru/http/" local="130013632200000000" remote="130013632200000000" />
<file name="header5.png" server="ftp.chado.1gb.ru/http/" local="130013632200000000" remote="130013632200000000" />
<file name="Bottom_texture.jpg" server="ftp.chado.1gb.ru/http/" local="130013632200000000" remote="130013632200000000" />
<file name="header (РєРѕРїРёСЏ).png" server="ftp.chado.1gb.ru/http/" local="130013632200000000" remote="130013632200000000" />
<file name="header4.png" server="ftp.chado.1gb.ru/http/" local="130013632200000000" remote="130013632200000000" />
<file name="header3.png" server="ftp.chado.1gb.ru/http/" local="130013632200000000" remote="130013632200000000" />
</dwsync>